setup.cfg
setup.py
scryunix/__init__.py
scryunix/scryunix.py
scryunix.egg-info/PKG-INFO
scryunix.egg-info/SOURCES.txt
scryunix.egg-info/dependency_links.txt
scryunix.egg-info/requires.txt
scryunix.egg-info/top_level.txt