Metadata-Version: 1.1
Name: scryunix
Version: 1.0
Summary: A simple terminal tool to fetch MTG card info
Home-page: https://github.com/Mendess2526/scryunix
Author: Mendess2526
Author-email: pedro.mendes.26@gmail.com
License: UNKNOWN
Download-URL: https://github.com/Mendess2526/scryunix/archive/scry.zip
Keywords: mtg,card,fetch,search,terminal,unix
Platform: UNKNOWN
